panel_gwalker/__init__.py
panel_gwalker/__version.py
panel_gwalker/_gwalker.js
panel_gwalker/_gwalker.py
panel_gwalker/_pygwalker.py
panel_gwalker/_tabular_data.py
panel_gwalker/_utils.py
panel_gwalker/_version.py
panel_gwalker/py.typed
panel_gwalker/dist/panel-gwalker.bundle.js
panel_graphic_walker-0.6.5.dist-info/METADATA
panel_graphic_walker-0.6.5.dist-info/WHEEL
panel_graphic_walker-0.6.5.dist-info/licenses/LICENSE.md
panel_graphic_walker-0.6.5.dist-info/RECORD
