Metadata-Version: 2.4
Name: panel-graphic-walker
Version: 0.6.5
Summary: A project providing a Graphic Walker Pane for use with HoloViz Panel.
Project-URL: Homepage, https://github.com/panel-extensions/panel-graphic-walker
Project-URL: Source, https://github.com/panel-extensions/panel-graphic-walker
Author-email: Philipp Rudiger <philipp.jfr@gmail.com>, Marc Skov Madsen <marc.skov.madsen@gmail.com>
License-File: LICENSE.md
Classifier: Development Status :: 5 - Production/Stable
Classifier: Intended Audience :: Developers
Classifier: Intended Audience :: Science/Research
Classifier: License :: OSI Approved :: BSD License
Classifier: Natural Language :: English
Classifier: Operating System :: OS Independent
Classifier: Programming Language :: Python :: 3
Classifier: Programming Language :: Python :: 3.10
Classifier: Programming Language :: Python :: 3.11
Classifier: Programming Language :: Python :: 3.12
Classifier: Programming Language :: Python :: 3.13
Classifier: Topic :: Scientific/Engineering
Classifier: Topic :: Software Development :: Libraries
Requires-Python: >=3.10
Requires-Dist: narwhals
Requires-Dist: panel>=1.6.1
Provides-Extra: dev
Requires-Dist: jedi-language-server; (sys_platform == 'linux') and extra == 'dev'
Requires-Dist: mypy; extra == 'dev'
Requires-Dist: pandas-stubs; extra == 'dev'
Requires-Dist: pre-commit; extra == 'dev'
Requires-Dist: pytest; extra == 'dev'
Requires-Dist: ruff; extra == 'dev'
Requires-Dist: types-requests; extra == 'dev'
Requires-Dist: watchfiles; extra == 'dev'
Provides-Extra: examples
Requires-Dist: dask[dataframe]; extra == 'examples'
Requires-Dist: duckdb; extra == 'examples'
Requires-Dist: fastparquet; extra == 'examples'
Requires-Dist: gw-dsl-parser; extra == 'examples'
Requires-Dist: ibis-framework[duckdb,sqlite]; extra == 'examples'
Requires-Dist: polars; extra == 'examples'
Requires-Dist: pygwalker>=0.4.9.11; extra == 'examples'
Requires-Dist: requests; extra == 'examples'
Provides-Extra: kernel
Requires-Dist: duckdb; (platform_system != 'Emscripten') and extra == 'kernel'
Requires-Dist: gw-dsl-parser; (platform_system != 'Emscripten') and extra == 'kernel'
Requires-Dist: pygwalker>=0.4.9.11; (platform_system != 'Emscripten') and extra == 'kernel'
Provides-Extra: tests
Requires-Dist: aiohttp; extra == 'tests'
Requires-Dist: dask[dataframe]; extra == 'tests'
Requires-Dist: duckdb; extra == 'tests'
Requires-Dist: fastparquet; extra == 'tests'
Requires-Dist: gw-dsl-parser; extra == 'tests'
Requires-Dist: ibis-framework[duckdb,sqlite]; extra == 'tests'
Requires-Dist: polars; extra == 'tests'
Requires-Dist: pygwalker; extra == 'tests'
Requires-Dist: pytest; extra == 'tests'
Requires-Dist: pytest-asyncio; extra == 'tests'
Requires-Dist: requests; extra == 'tests'
